setup.py
J_Guesser_game/GuesserGame.py
J_Guesser_game/__init__.py
J_Guesser_game/numberGuesserGame.py
J_Guesser_game.egg-info/PKG-INFO
J_Guesser_game.egg-info/SOURCES.txt
J_Guesser_game.egg-info/dependency_links.txt
J_Guesser_game.egg-info/top_level.txt