Metadata-Version: 2.1
Name: J-Guesser-game
Version: 0.0.1
Summary: Description's package
Author: Author's name
